pokegym/__init__.py
pokegym/data.py
pokegym/environment.py
pokegym/pyboy_binding.py
pokegym/ram_map.py
pokegym/version.py
pokegym-0.2.0.dist-info/LICENSE
pokegym-0.2.0.dist-info/METADATA
pokegym-0.2.0.dist-info/WHEEL
pokegym-0.2.0.dist-info/top_level.txt
pokegym-0.2.0.dist-info/RECORD
